{
  "name": "mazowieckie",
  "gminas": [
    {
      "area": "118.64",
      "county": "ostrowski",
      "id": "969",
      "name": "Andrzejewo",
      "voivodeship": "mazowieckie"
    },
    {
      "area": "162.35",
      "county": "płoński",
      "id": "970",
      "name": "Baboszewo",
      "voivodeship": "mazowieckie"
    },
    {
      "area": "198.19",
      "county": "ostrołęcki",
      "id": "971",
      "name": "Baranowo",
      "voivodeship": "mazowieckie"
    },
    {
      "area": "75.37",
      "county": "grodziski",
      "id": "972",
      "name": "Baranów",
      "voivodeship": "mazowieckie"
    },
    {
      "area": "107.84",
      "county": "grójecki",
      "id": "973",
      "name": "Belsk Duży",
      "voivodeship": "mazowieckie"
    },
    {
      "area": "78.93",
      "county": "białobrzeski",
      "id": "974",
      "name": "Białobrzegi",
      "voivodeship": "mazowieckie"
    },
    {
      "area": "109.60",
      "county": "sokołowski",
      "id": "975",
      "name": "Bielany",
      "voivodeship": "mazowieckie"
    },
    {
      "area": "125.53",
      "county": "płocki",
      "id": "976",
      "name": "Bielsk",
      "voivodeship": "mazowieckie"
    },
    {
      "area": "122.02",
      "county": "żuromiński",
      "id": "977",
      "name": "Bieżuń",
      "voivodeship": "mazowieckie"
    },
    {
      "area": "135.23",
      "county": "grójecki",
      "id": "978",
      "name": "Błędów",
      "voivodeship": "mazowieckie"
    },
    {
      "area": "85.84",
      "county": "warszawski zachodni",
      "id": "979",
      "name": "Błonie",
      "voivodeship": "mazowieckie"
    },
    {
      "area": "136.81",
      "county": "płocki",
      "id": "980",
      "name": "Bodzanów",
      "voivodeship": "mazowieckie"
    },
    {
      "area": "89.13",
      "county": "ostrowski",
      "id": "981",
      "name": "Boguty-Pianki",
      "voivodeship": "mazowieckie"
    },
    {
      "area": "86.06",
      "county": "przysuski",
      "id": "982",
      "name": "Borkowice",
      "voivodeship": "mazowieckie"
    },
    {
      "area": "80.41",
      "county": "garwoliński",
      "id": "983",
      "name": "Borowie",
      "voivodeship": "mazowieckie"
    },
    {
      "area": "167.61",
      "county": "wyszkowski",
      "id": "984",
      "name": "Brańszczyk",
      "voivodeship": "mazowieckie"
    },
    {
      "area": "116.76",
      "county": "sochaczewski",
      "id": "985",
      "name": "Brochów",
      "voivodeship": "mazowieckie"
    },
    {
      "area": "110.21",
      "county": "ostrowski",
      "id": "986",
      "name": "Brok",
      "voivodeship": "mazowieckie"
    },
    {
      "area": "161.82",
      "county": "płocki",
      "id": "987",
      "name": "Brudzeń Duży",
      "voivodeship": "mazowieckie"
    },
    {
      "area": "69.16",
      "county": "pruszkowski",
      "id": "988",
      "name": "Brwinów",
      "voivodeship": "mazowieckie"
    },
    {
      "area": "117.11",
      "county": "płocki",
      "id": "989",
      "name": "Bulkowo",
      "voivodeship": "mazowieckie"
    },
    {
      "area": "95.74",
      "county": "miński",
      "id": "990",
      "name": "Cegłów",
      "voivodeship": "mazowieckie"
    },
    {
      "area": "88.92",
      "county": "otwocki",
      "id": "991",
      "name": "Celestynów",
      "voivodeship": "mazowieckie"
    },
    {
      "area": "110.83",
      "county": "sokołowski",
      "id": "992",
      "name": "Ceranów",
      "voivodeship": "mazowieckie"
    },
    {
      "area": "124.20",
      "county": "szydłowiecki",
      "id": "993",
      "name": "Chlewiska",
      "voivodeship": "mazowieckie"
    },
    {
      "area": "371.53",
      "county": "przasnyski",
      "id": "994",
      "name": "Chorzele",
      "voivodeship": "mazowieckie"
    },
    {
      "area": "88.82",
      "county": "lipski",
      "id": "995",
      "name": "Chotcza",
      "voivodeship": "mazowieckie"
    },
    {
      "area": "137.07",
      "county": "grójecki",
      "id": "996",
      "name": "Chynów",
      "voivodeship": "mazowieckie"
    },
    {
      "area": "32.51",
      "county": "ciechanowski",
      "id": "997",
      "name": "Ciechanów - gmina miejska",
      "voivodeship": "mazowieckie"
    },
    {
      "area": "140.23",
      "county": "ciechanowski",
      "id": "998",
      "name": "Ciechanów - gmina wiejska",
      "voivodeship": "mazowieckie"
    },
    {
      "area": "135.30",
      "county": "lipski",
      "id": "999",
      "name": "Ciepielów",
      "voivodeship": "mazowieckie"
    },
    {
      "area": "92.53",
      "county": "ostrołęcki",
      "id": "1000",
      "name": "Czarnia",
      "voivodeship": "mazowieckie"
    },
    {
      "area": "120.31",
      "county": "przasnyski",
      "id": "1001",
      "name": "Czernice Borowe",
      "voivodeship": "mazowieckie"
    },
    {
      "area": "171.13",
      "county": "ostrołęcki",
      "id": "1002",
      "name": "Czerwin",
      "voivodeship": "mazowieckie"
    },
    {
      "area": "146.07",
      "county": "płoński",
      "id": "1003",
      "name": "Czerwińsk nad Wisłą",
      "voivodeship": "mazowieckie"
    },
    {
      "area": "110.59",
      "county": "makowski",
      "id": "1004",
      "name": "Czerwonka",
      "voivodeship": "mazowieckie"
    },
    {
      "area": "128.34",
      "county": "nowodworski",
      "id": "1005",
      "name": "Czosnów",
      "voivodeship": "mazowieckie"
    },
    {
      "area": "109.05",
      "county": "wołomiński",
      "id": "1006",
      "name": "Dąbrówka",
      "voivodeship": "mazowieckie"
    },
    {
      "area": "77.88",
      "county": "miński",
      "id": "1007",
      "name": "Dębe Wielkie",
      "voivodeship": "mazowieckie"
    },
    {
      "area": "167.45",
      "county": "wyszkowski",
      "id": "1008",
      "name": "Długosiodło",
      "voivodeship": "mazowieckie"
    },
    {
      "area": "124.85",
      "county": "miński",
      "id": "1009",
      "name": "Dobre",
      "voivodeship": "mazowieckie"
    },
    {
      "area": "46.87",
      "county": "siedlecki",
      "id": "1010",
      "name": "Domanice",
      "voivodeship": "mazowieckie"
    },
    {
      "area": "143.19",
      "county": "płocki",
      "id": "1011",
      "name": "Drobin",
      "voivodeship": "mazowieckie"
    },
    {
      "area": "102.10",
      "county": "płoński",
      "id": "1012",
      "name": "Dzierzążnia",
      "voivodeship": "mazowieckie"
    },
    {
      "area": "150.63",
      "county": "mławski",
      "id": "1013",
      "name": "Dzierzgowo",
      "voivodeship": "mazowieckie"
    },
    {
      "area": "74.01",
      "county": "kozienicki",
      "id": "1014",
      "name": "Garbatka-Letnisko",
      "voivodeship": "mazowieckie"
    },
    {
      "area": "22.08",
      "county": "garwoliński",
      "id": "1015",
      "name": "Garwolin - gmina miejska",
      "voivodeship": "mazowieckie"
    },
    {
      "area": "136.00",
      "county": "garwoliński",
      "id": "1016",
      "name": "Garwolin - gmina wiejska",
      "voivodeship": "mazowieckie"
    },
    {
      "area": "146.71",
      "county": "płocki",
      "id": "1017",
      "name": "Gąbin",
      "voivodeship": "mazowieckie"
    },
    {
      "area": "79.17",
      "county": "przysuski",
      "id": "1018",
      "name": "Gielniów",
      "voivodeship": "mazowieckie"
    },
    {
      "area": "153.49",
      "county": "ciechanowski",
      "id": "1019",
      "name": "Glinojeck",
      "voivodeship": "mazowieckie"
    },
    {
      "area": "186.26",
      "county": "kozienicki",
      "id": "1020",
      "name": "Głowaczów",
      "voivodeship": "mazowieckie"
    },
    {
      "area": "84.29",
      "county": "kozienicki",
      "id": "1021",
      "name": "Gniewoszów",
      "voivodeship": "mazowieckie"
    },
    {
      "area": "110.55",
      "county": "ciechanowski",
      "id": "1022",
      "name": "Gołymin-Ośrodek",
      "voivodeship": "mazowieckie"
    },
    {
      "area": "32.31",
      "county": "gostyniński",
      "id": "1023",
      "name": "Gostynin - gmina miejska",
      "voivodeship": "mazowieckie"
    },
    {
      "area": "270.69",
      "county": "gostyniński",
      "id": "1024",
      "name": "Gostynin - gmina wiejska",
      "voivodeship": "mazowieckie"
    },
    {
      "area": "56.99",
      "county": "grójecki",
      "id": "1025",
      "name": "Goszczyn",
      "voivodeship": "mazowieckie"
    },
    {
      "area": "218.93",
      "county": "ostrołęcki",
      "id": "1026",
      "name": "Goworowo",
      "voivodeship": "mazowieckie"
    },
    {
      "area": "126.70",
      "county": "sierpecki",
      "id": "1027",
      "name": "Gozdowo",
      "voivodeship": "mazowieckie"
    },
    {
      "area": "145.11",
      "county": "piaseczyński",
      "id": "1028",
      "name": "Góra Kalwaria",
      "voivodeship": "mazowieckie"
    },
    {
      "area": "90.84",
      "county": "garwoliński",
      "id": "1029",
      "name": "Górzno",
      "voivodeship": "mazowieckie"
    },
    {
      "area": "77.76",
      "county": "radomski",
      "id": "1030",
      "name": "Gózd",
      "voivodeship": "mazowieckie"
    },
    {
      "area": "124.66",
      "county": "kozienicki",
      "id": "1031",
      "name": "Grabów nad Pilicą",
      "voivodeship": "mazowieckie"
    },
    {
      "area": "130.75",
      "county": "węgrowski",
      "id": "1032",
      "name": "Grębków",
      "voivodeship": "mazowieckie"
    },
    {
      "area": "107.03",
      "county": "grodziski",
      "id": "1033",
      "name": "Grodzisk Mazowiecki",
      "voivodeship": "mazowieckie"
    },
    {
      "area": "120.64",
      "county": "grójecki",
      "id": "1034",
      "name": "Grójec",
      "voivodeship": "mazowieckie"
    },
    {
      "area": "96.69",
      "county": "ciechanowski",
      "id": "1035",
      "name": "Grudusk",
      "voivodeship": "mazowieckie"
    },
    {
      "area": "104.44",
      "county": "pułtuski",
      "id": "1036",
      "name": "Gzy",
      "voivodeship": "mazowieckie"
    },
    {
      "area": "63.09",
      "county": "miński",
      "id": "1037",
      "name": "Halinów",
      "voivodeship": "mazowieckie"
    },
    {
      "area": "117.61",
      "county": "łosicki",
      "id": "1038",
      "name": "Huszlew",
      "voivodeship": "mazowieckie"
    },
    {
      "area": "128.49",
      "county": "sochaczewski",
      "id": "1039",
      "name": "Iłów",
      "voivodeship": "mazowieckie"
    },
    {
      "area": "255.82",
      "county": "radomski",
      "id": "1040",
      "name": "Iłża",
      "voivodeship": "mazowieckie"
    },
    {
      "area": "64.98",
      "county": "warszawski zachodni",
      "id": "1041",
      "name": "Izabelin",
      "voivodeship": "mazowieckie"
    },
    {
      "area": "64.55",
      "county": "legionowski",
      "id": "1042",
      "name": "Jabłonna",
      "voivodeship": "mazowieckie"
    },
    {
      "area": "149.40",
      "county": "sokołowski",
      "id": "1043",
      "name": "Jabłonna Lacka",
      "voivodeship": "mazowieckie"
    },
    {
      "area": "116.87",
      "county": "wołomiński",
      "id": "1044",
      "name": "Jadów",
      "voivodeship": "mazowieckie"
    },
    {
      "area": "55.24",
      "county": "grodziski",
      "id": "1045",
      "name": "Jaktorów",
      "voivodeship": "mazowieckie"
    },
    {
      "area": "87.23",
      "county": "miński",
      "id": "1046",
      "name": "Jakubów",
      "voivodeship": "mazowieckie"
    },
    {
      "area": "107.83",
      "county": "grójecki",
      "id": "1047",
      "name": "Jasieniec",
      "voivodeship": "mazowieckie"
    },
    {
      "area": "54.79",
      "county": "szydłowiecki",
      "id": "1048",
      "name": "Jastrząb",
      "voivodeship": "mazowieckie"
    },
    {
      "area": "89.51",
      "county": "radomski",
      "id": "1049",
      "name": "Jastrzębia",
      "voivodeship": "mazowieckie"
    },
    {
      "area": "138.72",
      "county": "radomski",
      "id": "1050",
      "name": "Jedlińsk",
      "voivodeship": "mazowieckie"
    },
    {
      "area": "65.57",
      "county": "radomski",
      "id": "1051",
      "name": "Jedlnia-Letnisko",
      "voivodeship": "mazowieckie"
    },
    {
      "area": "231.57",
      "county": "przasnyski",
      "id": "1052",
      "name": "Jednorożec",
      "voivodeship": "mazowieckie"
    },
    {
      "area": "72.64",
      "county": "płoński",
      "id": "1053",
      "name": "Joniec",
      "voivodeship": "mazowieckie"
    },
    {
      "area": "23.92",
      "county": "otwocki",
      "id": "1054",
      "name": "Józefów",
      "voivodeship": "mazowieckie"
    },
    {
      "area": "258.94",
      "county": "ostrołęcki",
      "id": "1055",
      "name": "Kadzidło",
      "voivodeship": "mazowieckie"
    },
    {
      "area": "94.52",
      "county": "miński",
      "id": "1056",
      "name": "Kałuszyn",
      "voivodeship": "mazowieckie"
    },
    {
      "area": "84.25",
      "county": "warszawski zachodni",
      "id": "1057",
      "name": "Kampinos",
      "voivodeship": "mazowieckie"
    },
    {
      "area": "81.49",
      "county": "otwocki",
      "id": "1058",
      "name": "Karczew",
      "voivodeship": "mazowieckie"
    },
    {
      "area": "129.38",
      "county": "makowski",
      "id": "1059",
      "name": "Karniewo",
      "voivodeship": "mazowieckie"
    },
    {
      "area": "94.76",
      "county": "zwoleński",
      "id": "1060",
      "name": "Kazanów",
      "voivodeship": "mazowieckie"
    },
    {
      "area": "85.79",
      "county": "wołomiński",
      "id": "1061",
      "name": "Klembów",
      "voivodeship": "mazowieckie"
    },
    {
      "area": "90.46",
      "county": "przysuski",
      "id": "1062",
      "name": "Klwów",
      "voivodeship": "mazowieckie"
    },
    {
      "area": "20.05",
      "county": "wołomiński",
      "id": "1063",
      "name": "Kobyłka",
      "voivodeship": "mazowieckie"
    },
    {
      "area": "106.44",
      "county": "otwocki",
      "id": "1064",
      "name": "Kołbiel",
      "voivodeship": "mazowieckie"
    },
    {
      "area": "78.28",
      "county": "piaseczyński",
      "id": "1065",
      "name": "Konstancin-Jeziorna",
      "voivodeship": "mazowieckie"
    },
    {
      "area": "105.14",
      "county": "siedlecki",
      "id": "1066",
      "name": "Korczew",
      "voivodeship": "mazowieckie"
    },
    {
      "area": "180.54",
      "county": "węgrowski",
      "id": "1067",
      "name": "Korytnica",
      "voivodeship": "mazowieckie"
    },
    {
      "area": "200.17",
      "county": "sokołowski",
      "id": "1068",
      "name": "Kosów Lacki",
      "voivodeship": "mazowieckie"
    },
    {
      "area": "149.87",
      "county": "siedlecki",
      "id": "1069",
      "name": "Kotuń",
      "voivodeship": "mazowieckie"
    },
    {
      "area": "74.71",
      "county": "radomski",
      "id": "1070",
      "name": "Kowala",
      "voivodeship": "mazowieckie"
    },
    {
      "area": "245.56",
      "county": "kozienicki",
      "id": "1071",
      "name": "Kozienice",
      "voivodeship": "mazowieckie"
    },
    {
      "area": "100.94",
      "county": "przasnyski",
      "id": "1072",
      "name": "Krasne",
      "voivodeship": "mazowieckie"
    },
    {
      "area": "166.96",
      "county": "makowski",
      "id": "1073",
      "name": "Krasnosielc",
      "voivodeship": "mazowieckie"
    },
    {
      "area": "184.40",
      "county": "przasnyski",
      "id": "1074",
      "name": "Krzynowłoga Mała",
      "voivodeship": "mazowieckie"
    },
    {
      "area": "121.64",
      "county": "żuromiński",
      "id": "1075",
      "name": "Kuczbork-Osada",
      "voivodeship": "mazowieckie"
    },
    {
      "area": "114.15",
      "county": "miński",
      "id": "1076",
      "name": "Latowicz",
      "voivodeship": "mazowieckie"
    },
    {
      "area": "13.60",
      "county": "legionowski",
      "id": "1077",
      "name": "Legionowo",
      "voivodeship": "mazowieckie"
    },
    {
      "area": "197.00",
      "county": "ostrołęcki",
      "id": "1078",
      "name": "Lelis",
      "voivodeship": "mazowieckie"
    },
    {
      "area": "158.84",
      "county": "nowodworski",
      "id": "1079",
      "name": "Leoncin",
      "voivodeship": "mazowieckie"
    },
    {
      "area": "125.03",
      "county": "warszawski zachodni",
      "id": "1080",
      "name": "Leszno",
      "voivodeship": "mazowieckie"
    },
    {
      "area": "69.17",
      "county": "piaseczyński",
      "id": "1081",
      "name": "Lesznowola",
      "voivodeship": "mazowieckie"
    },
    {
      "area": "114.21",
      "county": "mławski",
      "id": "1082",
      "name": "Lipowiec Kościelny",
      "voivodeship": "mazowieckie"
    },
    {
      "area": "135.21",
      "county": "lipski",
      "id": "1083",
      "name": "Lipsko",
      "voivodeship": "mazowieckie"
    },
    {
      "area": "169.56",
      "county": "węgrowski",
      "id": "1084",
      "name": "Liw",
      "voivodeship": "mazowieckie"
    },
    {
      "area": "190.81",
      "county": "żuromiński",
      "id": "1085",
      "name": "Lubowidz",
      "voivodeship": "mazowieckie"
    },
    {
      "area": "126.03",
      "county": "żuromiński",
      "id": "1086",
      "name": "Lutocin",
      "voivodeship": "mazowieckie"
    },
    {
      "area": "15.35",
      "county": "garwoliński",
      "id": "1087",
      "name": "Łaskarzew - gmina miejska",
      "voivodeship": "mazowieckie"
    },
    {
      "area": "87.53",
      "county": "garwoliński",
      "id": "1088",
      "name": "Łaskarzew - gmina wiejska",
      "voivodeship": "mazowieckie"
    },
    {
      "area": "93.74",
      "county": "płocki",
      "id": "1089",
      "name": "Łąck",
      "voivodeship": "mazowieckie"
    },
    {
      "area": "194.98",
      "county": "węgrowski",
      "id": "1090",
      "name": "Łochów",
      "voivodeship": "mazowieckie"
    },
    {
      "area": "38.06",
      "county": "warszawski zachodni",
      "id": "1091",
      "name": "Łomianki",
      "voivodeship": "mazowieckie"
    },
    {
      "area": "121.22",
      "county": "łosicki",
      "id": "1092",
      "name": "Łosice",
      "voivodeship": "mazowieckie"
    },
    {
      "area": "246.45",
      "county": "ostrołęcki",
      "id": "1093",
      "name": "Łyse",
      "voivodeship": "mazowieckie"
    },
    {
      "area": "172.67",
      "county": "garwoliński",
      "id": "1094",
      "name": "Maciejowice",
      "voivodeship": "mazowieckie"
    },
    {
      "area": "140.92",
      "county": "kozienicki",
      "id": "1095",
      "name": "Magnuszew",
      "voivodeship": "mazowieckie"
    },
    {
      "area": "10.30",
      "county": "makowski",
      "id": "1096",
      "name": "Maków Mazowiecki",
      "voivodeship": "mazowieckie"
    },
    {
      "area": "108.91",
      "county": "płocki",
      "id": "1097",
      "name": "Mała Wieś",
      "voivodeship": "mazowieckie"
    },
    {
      "area": "134.08",
      "county": "ostrowski",
      "id": "1098",
      "name": "Małkinia Górna",
      "voivodeship": "mazowieckie"
    },
    {
      "area": "26.01",
      "county": "wołomiński",
      "id": "1099",
      "name": "Marki",
      "voivodeship": "mazowieckie"
    },
    {
      "area": "85.24",
      "county": "garwoliński",
      "id": "1100",
      "name": "Miastków Kościelny",
      "voivodeship": "mazowieckie"
    },
    {
      "area": "34.88",
      "county": "pruszkowski",
      "id": "1101",
      "name": "Michałowice",
      "voivodeship": "mazowieckie"
    },
    {
      "area": "115.78",
      "county": "węgrowski",
      "id": "1102",
      "name": "Miedzna",
      "voivodeship": "mazowieckie"
    },
    {
      "area": "13.52",
      "county": "grodziski",
      "id": "1103",
      "name": "Milanówek",
      "voivodeship": "mazowieckie"
    },
    {
      "area": "13.12",
      "county": "miński",
      "id": "1104",
      "name": "Mińsk Mazowiecki - gmina miejska",
      "voivodeship": "mazowieckie"
    },
    {
      "area": "112.28",
      "county": "miński",
      "id": "1105",
      "name": "Mińsk Mazowiecki - gmina wiejska",
      "voivodeship": "mazowieckie"
    },
    {
      "area": "53.17",
      "county": "szydłowiecki",
      "id": "1106",
      "name": "Mirów",
      "voivodeship": "mazowieckie"
    },
    {
      "area": "35.50",
      "county": "mławski",
      "id": "1107",
      "name": "Mława",
      "voivodeship": "mazowieckie"
    },
    {
      "area": "117.07",
      "county": "sochaczewski",
      "id": "1108",
      "name": "Młodzieszyn",
      "voivodeship": "mazowieckie"
    },
    {
      "area": "75.04",
      "county": "makowski",
      "id": "1109",
      "name": "Młynarze",
      "voivodeship": "mazowieckie"
    },
    {
      "area": "143.57",
      "county": "sierpecki",
      "id": "1110",
      "name": "Mochowo",
      "voivodeship": "mazowieckie"
    },
    {
      "area": "141.56",
      "county": "grójecki",
      "id": "1111",
      "name": "Mogielnica",
      "voivodeship": "mazowieckie"
    },
    {
      "area": "119.17",
      "county": "siedlecki",
      "id": "1112",
      "name": "Mokobody",
      "voivodeship": "mazowieckie"
    },
    {
      "area": "170.17",
      "county": "siedlecki",
      "id": "1113",
      "name": "Mordy",
      "voivodeship": "mazowieckie"
    },
    {
      "area": "145.24",
      "county": "miński",
      "id": "1114",
      "name": "Mrozy",
      "voivodeship": "mazowieckie"
    },
    {
      "area": "144.87",
      "county": "żyrardowski",
      "id": "1115",
      "name": "Mszczonów",
      "voivodeship": "mazowieckie"
    },
    {
      "area": "228.59",
      "county": "ostrołęcki",
      "id": "1116",
      "name": "Myszyniec",
      "voivodeship": "mazowieckie"
    },
    {
      "area": "73.40",
      "county": "pruszkowski",
      "id": "1117",
      "name": "Nadarzyn",
      "voivodeship": "mazowieckie"
    },
    {
      "area": "159.55",
      "county": "płoński",
      "id": "1118",
      "name": "Naruszewo",
      "voivodeship": "mazowieckie"
    },
    {
      "area": "202.47",
      "county": "nowodworski",
      "id": "1119",
      "name": "Nasielsk",
      "voivodeship": "mazowieckie"
    },
    {
      "area": "100.52",
      "county": "legionowski",
      "id": "1120",
      "name": "Nieporęt",
      "voivodeship": "mazowieckie"
    },
    {
      "area": "90.34",
      "county": "sochaczewski",
      "id": "1121",
      "name": "Nowa Sucha",
      "voivodeship": "mazowieckie"
    },
    {
      "area": "118.35",
      "county": "płoński",
      "id": "1122",
      "name": "Nowe Miasto",
      "voivodeship": "mazowieckie"
    },
    {
      "area": "158.47",
      "county": "grójecki",
      "id": "1123",
      "name": "Nowe Miasto nad Pilicą",
      "voivodeship": "mazowieckie"
    },
    {
      "area": "144.79",
      "county": "płocki",
      "id": "1124",
      "name": "Nowy Duninów",
      "voivodeship": "mazowieckie"
    },
    {
      "area": "28.27",
      "county": "nowodworski",
      "id": "1125",
      "name": "Nowy Dwór Mazowiecki",
      "voivodeship": "mazowieckie"
    },
    {
      "area": "96.23",
      "county": "ostrowski",
      "id": "1126",
      "name": "Nur",
      "voivodeship": "mazowieckie"
    },
    {
      "area": "139.73",
      "county": "pułtuski",
      "id": "1127",
      "name": "Obryte",
      "voivodeship": "mazowieckie"
    },
    {
      "area": "94.83",
      "county": "przysuski",
      "id": "1128",
      "name": "Odrzywół",
      "voivodeship": "mazowieckie"
    },
    {
      "area": "123.11",
      "county": "ciechanowski",
      "id": "1129",
      "name": "Ojrzeń",
      "voivodeship": "mazowieckie"
    },
    {
      "area": "87.34",
      "county": "łosicki",
      "id": "1130",
      "name": "Olszanka",
      "voivodeship": "mazowieckie"
    },
    {
      "area": "195.58",
      "county": "ostrołęcki",
      "id": "1131",
      "name": "Olszewo-Borki",
      "voivodeship": "mazowieckie"
    },
    {
      "area": "139.76",
      "county": "ciechanowski",
      "id": "1132",
      "name": "Opinogóra Górna",
      "voivodeship": "mazowieckie"
    },
    {
      "area": "81.91",
      "county": "szydłowiecki",
      "id": "1133",
      "name": "Orońsko",
      "voivodeship": "mazowieckie"
    },
    {
      "area": "67.50",
      "county": "otwocki",
      "id": "1134",
      "name": "Osieck",
      "voivodeship": "mazowieckie"
    },
    {
      "area": "29.47",
      "county": "prawa powiatu",
      "id": "1135",
      "name": "Ostrołęka",
      "voivodeship": "mazowieckie"
    },
    {
      "area": "22.09",
      "county": "ostrowski",
      "id": "1136",
      "name": "Ostrów Mazowiecka - gmina miejska",
      "voivodeship": "mazowieckie"
    },
    {
      "area": "283.71",
      "county": "ostrowski",
      "id": "1137",
      "name": "Ostrów Mazowiecka - gmina wiejska",
      "voivodeship": "mazowieckie"
    },
    {
      "area": "47.33",
      "county": "otwocki",
      "id": "1138",
      "name": "Otwock",
      "voivodeship": "mazowieckie"
    },
    {
      "area": "71.34",
      "county": "warszawski zachodni",
      "id": "1139",
      "name": "Ożarów Mazowiecki",
      "voivodeship": "mazowieckie"
    },
    {
      "area": "90.85",
      "county": "gostyniński",
      "id": "1140",
      "name": "Pacyna",
      "voivodeship": "mazowieckie"
    },
    {
      "area": "81.43",
      "county": "siedlecki",
      "id": "1141",
      "name": "Paprotnia",
      "voivodeship": "mazowieckie"
    },
    {
      "area": "64.31",
      "county": "garwoliński",
      "id": "1142",
      "name": "Parysów",
      "voivodeship": "mazowieckie"
    },
    {
      "area": "128.22",
      "county": "piaseczyński",
      "id": "1143",
      "name": "Piaseczno",
      "voivodeship": "mazowieckie"
    },
    {
      "area": "5.83",
      "county": "pruszkowski",
      "id": "1144",
      "name": "Piastów",
      "voivodeship": "mazowieckie"
    },
    {
      "area": "77.25",
      "county": "garwoliński",
      "id": "1145",
      "name": "Pilawa",
      "voivodeship": "mazowieckie"
    },
    {
      "area": "18.34",
      "county": "radomski",
      "id": "1146",
      "name": "Pionki - gmina miejska",
      "voivodeship": "mazowieckie"
    },
    {
      "area": "230.82",
      "county": "radomski",
      "id": "1147",
      "name": "Pionki - gmina wiejska",
      "voivodeship": "mazowieckie"
    },
    {
      "area": "128.97",
      "county": "łosicki",
      "id": "1148",
      "name": "Platerów",
      "voivodeship": "mazowieckie"
    },
    {
      "area": "88.06",
      "county": "prawa powiatu",
      "id": "1149",
      "name": "Płock",
      "voivodeship": "mazowieckie"
    },
    {
      "area": "134.96",
      "county": "makowski",
      "id": "1150",
      "name": "Płoniawy-Bramura",
      "voivodeship": "mazowieckie"
    },
    {
      "area": "11.38",
      "county": "płoński",
      "id": "1151",
      "name": "Płońsk - gmina miejska",
      "voivodeship": "mazowieckie"
    },
    {
      "area": "127.30",
      "county": "płoński",
      "id": "1152",
      "name": "Płońsk - gmina wiejska",
      "voivodeship": "mazowieckie"
    },
    {
      "area": "102.05",
      "county": "grójecki",
      "id": "1153",
      "name": "Pniewy",
      "voivodeship": "mazowieckie"
    },
    {
      "area": "10.10",
      "county": "grodziski",
      "id": "1154",
      "name": "Podkowa Leśna",
      "voivodeship": "mazowieckie"
    },
    {
      "area": "120.99",
      "county": "pułtuski",
      "id": "1155",
      "name": "Pokrzywnica",
      "voivodeship": "mazowieckie"
    },
    {
      "area": "112.35",
      "county": "zwoleński",
      "id": "1156",
      "name": "Policzna",
      "voivodeship": "mazowieckie"
    },
    {
      "area": "102.31",
      "county": "nowodworski",
      "id": "1157",
      "name": "Pomiechówek",
      "voivodeship": "mazowieckie"
    },
    {
      "area": "106.26",
      "county": "wołomiński",
      "id": "1158",
      "name": "Poświętne",
      "voivodeship": "mazowieckie"
    },
    {
      "area": "81.89",
      "county": "przysuski",
      "id": "1159",
      "name": "Potworów",
      "voivodeship": "mazowieckie"
    },
    {
      "area": "86.11",
      "county": "piaseczyński",
      "id": "1160",
      "name": "Prażmów",
      "voivodeship": "mazowieckie"
    },
    {
      "area": "120.74",
      "county": "białobrzeski",
      "id": "1161",
      "name": "Promna",
      "voivodeship": "mazowieckie"
    },
    {
      "area": "19.15",
      "county": "pruszkowski",
      "id": "1162",
      "name": "Pruszków",
      "voivodeship": "mazowieckie"
    },
    {
      "area": "25.16",
      "county": "przasnyski",
      "id": "1163",
      "name": "Przasnysz - gmina miejska",
      "voivodeship": "mazowieckie"
    },
    {
      "area": "183.91",
      "county": "przasnyski",
      "id": "1164",
      "name": "Przasnysz - gmina wiejska",
      "voivodeship": "mazowieckie"
    },
    {
      "area": "117.13",
      "county": "siedlecki",
      "id": "1165",
      "name": "Przesmyki",
      "voivodeship": "mazowieckie"
    },
    {
      "area": "130.89",
      "county": "zwoleński",
      "id": "1166",
      "name": "Przyłęk",
      "voivodeship": "mazowieckie"
    },
    {
      "area": "181.31",
      "county": "przysuski",
      "id": "1167",
      "name": "Przysucha",
      "voivodeship": "mazowieckie"
    },
    {
      "area": "134.12",
      "county": "radomski",
      "id": "1168",
      "name": "Przytyk",
      "voivodeship": "mazowieckie"
    },
    {
      "area": "133.72",
      "county": "pułtuski",
      "id": "1169",
      "name": "Pułtusk",
      "voivodeship": "mazowieckie"
    },
    {
      "area": "142.41",
      "county": "żyrardowski",
      "id": "1170",
      "name": "Puszcza Mariańska",
      "voivodeship": "mazowieckie"
    },
    {
      "area": "3.82",
      "county": "płoński",
      "id": "1171",
      "name": "Raciąż - gmina miejska",
      "voivodeship": "mazowieckie"
    },
    {
      "area": "248.79",
      "county": "płoński",
      "id": "1172",
      "name": "Raciąż - gmina wiejska",
      "voivodeship": "mazowieckie"
    },
    {
      "area": "111.71",
      "county": "prawa powiatu",
      "id": "1173",
      "name": "Radom",
      "voivodeship": "mazowieckie"
    },
    {
      "area": "104.32",
      "county": "płocki",
      "id": "1174",
      "name": "Radzanowo",
      "voivodeship": "mazowieckie"
    },
    {
      "area": "82.59",
      "county": "białobrzeski",
      "id": "1175",
      "name": "Radzanów (pow. białobrzeski)",
      "voivodeship": "mazowieckie"
    },
    {
      "area": "98.70",
      "county": "mławski",
      "id": "1176",
      "name": "Radzanów (pow. mławski)",
      "voivodeship": "mazowieckie"
    },
    {
      "area": "80.06",
      "county": "żyrardowski",
      "id": "1177",
      "name": "Radziejowice",
      "voivodeship": "mazowieckie"
    },
    {
      "area": "130.93",
      "county": "wołomiński",
      "id": "1178",
      "name": "Radzymin",
      "voivodeship": "mazowieckie"
    },
    {
      "area": "43.89",
      "county": "pruszkowski",
      "id": "1179",
      "name": "Raszyn",
      "voivodeship": "mazowieckie"
    },
    {
      "area": "111.29",
      "county": "ciechanowski",
      "id": "1180",
      "name": "Regimin",
      "voivodeship": "mazowieckie"
    },
    {
      "area": "168.79",
      "county": "sokołowski",
      "id": "1181",
      "name": "Repki",
      "voivodeship": "mazowieckie"
    },
    {
      "area": "115.08",
      "county": "sierpecki",
      "id": "1182",
      "name": "Rościszewo",
      "voivodeship": "mazowieckie"
    },
    {
      "area": "84.10",
      "county": "makowski",
      "id": "1183",
      "name": "Różan",
      "voivodeship": "mazowieckie"
    },
    {
      "area": "82.93",
      "county": "przysuski",
      "id": "1184",
      "name": "Rusinów",
      "voivodeship": "mazowieckie"
    },
    {
      "area": "72.84",
      "county": "sochaczewski",
      "id": "1185",
      "name": "Rybno",
      "voivodeship": "mazowieckie"
    },
    {
      "area": "167.42",
      "county": "wyszkowski",
      "id": "1186",
      "name": "Rząśnik",
      "voivodeship": "mazowieckie"
    },
    {
      "area": "103.69",
      "county": "lipski",
      "id": "1187",
      "name": "Rzeczniów",
      "voivodeship": "mazowieckie"
    },
    {
      "area": "135.20",
      "county": "ostrołęcki",
      "id": "1188",
      "name": "Rzekuń",
      "voivodeship": "mazowieckie"
    },
    {
      "area": "111.72",
      "county": "makowski",
      "id": "1189",
      "name": "Rzewnie",
      "voivodeship": "mazowieckie"
    },
    {
      "area": "107.92",
      "county": "sokołowski",
      "id": "1190",
      "name": "Sabnie",
      "voivodeship": "mazowieckie"
    },
    {
      "area": "144.72",
      "county": "węgrowski",
      "id": "1191",
      "name": "Sadowne",
      "voivodeship": "mazowieckie"
    },
    {
      "area": "94.57",
      "county": "gostyniński",
      "id": "1192",
      "name": "Sanniki",
      "voivodeship": "mazowieckie"
    },
    {
      "area": "197.30",
      "county": "łosicki",
      "id": "1193",
      "name": "Sarnaki",
      "voivodeship": "mazowieckie"
    },
    {
      "area": "108.96",
      "county": "legionowski",
      "id": "1194",
      "name": "Serock",
      "voivodeship": "mazowieckie"
    },
    {
      "area": "61.26",
      "county": "kozienicki",
      "id": "1195",
      "name": "Sieciechów",
      "voivodeship": "mazowieckie"
    },
    {
      "area": "31.87",
      "county": "siedlecki",
      "id": "1196",
      "name": "Siedlce - gmina miejska",
      "voivodeship": "mazowieckie"
    },
    {
      "area": "141.54",
      "county": "siedlecki",
      "id": "1197",
      "name": "Siedlce - gmina wiejska",
      "voivodeship": "mazowieckie"
    },
    {
      "area": "112.07",
      "county": "żuromiński",
      "id": "1198",
      "name": "Siemiątkowo",
      "voivodeship": "mazowieckie"
    },
    {
      "area": "110.73",
      "county": "miński",
      "id": "1199",
      "name": "Siennica",
      "voivodeship": "mazowieckie"
    },
    {
      "area": "147.15",
      "county": "lipski",
      "id": "1200",
      "name": "Sienno",
      "voivodeship": "mazowieckie"
    },
    {
      "area": "18.60",
      "county": "sierpecki",
      "id": "1201",
      "name": "Sierpc - gmina miejska",
      "voivodeship": "mazowieckie"
    },
    {
      "area": "150.23",
      "county": "sierpecki",
      "id": "1202",
      "name": "Sierpc - gmina wiejska",
      "voivodeship": "mazowieckie"
    },
    {
      "area": "171.41",
      "county": "radomski",
      "id": "1203",
      "name": "Skaryszew",
      "voivodeship": "mazowieckie"
    },
    {
      "area": "118.91",
      "county": "siedlecki",
      "id": "1204",
      "name": "Skórzec",
      "voivodeship": "mazowieckie"
    },
    {
      "area": "94.47",
      "county": "płocki",
      "id": "1205",
      "name": "Słubice",
      "voivodeship": "mazowieckie"
    },
    {
      "area": "74.71",
      "county": "płocki",
      "id": "1206",
      "name": "Słupno",
      "voivodeship": "mazowieckie"
    },
    {
      "area": "97.37",
      "county": "otwocki",
      "id": "1207",
      "name": "Sobienie-Jeziory",
      "voivodeship": "mazowieckie"
    },
    {
      "area": "94.83",
      "county": "garwoliński",
      "id": "1208",
      "name": "Sobolew",
      "voivodeship": "mazowieckie"
    },
    {
      "area": "26.13",
      "county": "sochaczewski",
      "id": "1209",
      "name": "Sochaczew - gmina miejska",
      "voivodeship": "mazowieckie"
    },
    {
      "area": "91.41",
      "county": "sochaczewski",
      "id": "1210",
      "name": "Sochaczew - gmina wiejska",
      "voivodeship": "mazowieckie"
    },
    {
      "area": "119.67",
      "county": "płoński",
      "id": "1211",
      "name": "Sochocin",
      "voivodeship": "mazowieckie"
    },
    {
      "area": "17.50",
      "county": "sokołowski",
      "id": "1212",
      "name": "Sokołów Podlaski - gmina miejska",
      "voivodeship": "mazowieckie"
    },
    {
      "area": "137.18",
      "county": "sokołowski",
      "id": "1213",
      "name": "Sokołów Podlaski - gmina wiejska",
      "voivodeship": "mazowieckie"
    },
    {
      "area": "130.35",
      "county": "lipski",
      "id": "1214",
      "name": "Solec nad Wisłą",
      "voivodeship": "mazowieckie"
    },
    {
      "area": "116.38",
      "county": "wyszkowski",
      "id": "1215",
      "name": "Somianka",
      "voivodeship": "mazowieckie"
    },
    {
      "area": "154.99",
      "county": "ciechanowski",
      "id": "1216",
      "name": "Sońsk",
      "voivodeship": "mazowieckie"
    },
    {
      "area": "106.01",
      "county": "miński",
      "id": "1217",
      "name": "Stanisławów",
      "voivodeship": "mazowieckie"
    },
    {
      "area": "111.12",
      "county": "płocki",
      "id": "1218",
      "name": "Stara Biała",
      "voivodeship": "mazowieckie"
    },
    {
      "area": "96.24",
      "county": "białobrzeski",
      "id": "1219",
      "name": "Stara Błotnica",
      "voivodeship": "mazowieckie"
    },
    {
      "area": "119.33",
      "county": "łosicki",
      "id": "1220",
      "name": "Stara Kornica",
      "voivodeship": "mazowieckie"
    },
    {
      "area": "63.49",
      "county": "warszawski zachodni",
      "id": "1221",
      "name": "Stare Babice",
      "voivodeship": "mazowieckie"
    },
    {
      "area": "137.55",
      "county": "płocki",
      "id": "1222",
      "name": "Staroźreby",
      "voivodeship": "mazowieckie"
    },
    {
      "area": "109.16",
      "county": "ostrowski",
      "id": "1223",
      "name": "Stary Lubotyń",
      "voivodeship": "mazowieckie"
    },
    {
      "area": "130.03",
      "county": "sokołowski",
      "id": "1224",
      "name": "Sterdyń",
      "voivodeship": "mazowieckie"
    },
    {
      "area": "144.31",
      "county": "węgrowski",
      "id": "1225",
      "name": "Stoczek",
      "voivodeship": "mazowieckie"
    },
    {
      "area": "107.70",
      "county": "wołomiński",
      "id": "1226",
      "name": "Strachówka",
      "voivodeship": "mazowieckie"
    },
    {
      "area": "156.47",
      "county": "białobrzeski",
      "id": "1227",
      "name": "Stromiec",
      "voivodeship": "mazowieckie"
    },
    {
      "area": "214.23",
      "county": "mławski",
      "id": "1228",
      "name": "Strzegowo",
      "voivodeship": "mazowieckie"
    },
    {
      "area": "118.04",
      "county": "mławski",
      "id": "1229",
      "name": "Stupsk",
      "voivodeship": "mazowieckie"
    },
    {
      "area": "100.71",
      "county": "siedlecki",
      "id": "1230",
      "name": "Suchożebry",
      "voivodeship": "mazowieckie"
    },
    {
      "area": "19.51",
      "county": "miński",
      "id": "1231",
      "name": "Sulejówek",
      "voivodeship": "mazowieckie"
    },
    {
      "area": "128.58",
      "county": "makowski",
      "id": "1232",
      "name": "Sypniewo",
      "voivodeship": "mazowieckie"
    },
    {
      "area": "127.14",
      "county": "gostyniński",
      "id": "1233",
      "name": "Szczawin Kościelny",
      "voivodeship": "mazowieckie"
    },
    {
      "area": "112.62",
      "county": "sierpecki",
      "id": "1234",
      "name": "Szczutowo",
      "voivodeship": "mazowieckie"
    },
    {
      "area": "112.93",
      "county": "makowski",
      "id": "1235",
      "name": "Szelków",
      "voivodeship": "mazowieckie"
    },
    {
      "area": "109.66",
      "county": "mławski",
      "id": "1236",
      "name": "Szreńsk",
      "voivodeship": "mazowieckie"
    },
    {
      "area": "46.71",
      "county": "ostrowski",
      "id": "1237",
      "name": "Szulborze Wielkie",
      "voivodeship": "mazowieckie"
    },
    {
      "area": "138.15",
      "county": "szydłowiecki",
      "id": "1238",
      "name": "Szydłowiec",
      "voivodeship": "mazowieckie"
    },
    {
      "area": "122.21",
      "county": "mławski",
      "id": "1239",
      "name": "Szydłowo",
      "voivodeship": "mazowieckie"
    },
    {
      "area": "93.04",
      "county": "pułtuski",
      "id": "1240",
      "name": "Świercze",
      "voivodeship": "mazowieckie"
    },
    {
      "area": "114.15",
      "county": "piaseczyński",
      "id": "1241",
      "name": "Tarczyn",
      "voivodeship": "mazowieckie"
    },
    {
      "area": "72.12",
      "county": "zwoleński",
      "id": "1242",
      "name": "Tczów",
      "voivodeship": "mazowieckie"
    },
    {
      "area": "87.98",
      "county": "sochaczewski",
      "id": "1243",
      "name": "Teresin",
      "voivodeship": "mazowieckie"
    },
    {
      "area": "102.83",
      "county": "wołomiński",
      "id": "1244",
      "name": "Tłuszcz",
      "voivodeship": "mazowieckie"
    },
    {
      "area": "151.01",
      "county": "garwoliński",
      "id": "1245",
      "name": "Trojanów",
      "voivodeship": "mazowieckie"
    },
    {
      "area": "156.31",
      "county": "ostrołęcki",
      "id": "1246",
      "name": "Troszyn",
      "voivodeship": "mazowieckie"
    },
    {
      "area": "201.14",
      "county": "grójecki",
      "id": "1247",
      "name": "Warka",
      "voivodeship": "mazowieckie"
    },
    {
      "area": "516.90",
      "county": "prawa powiatu",
      "id": "1248",
      "name": "Warszawa",
      "voivodeship": "mazowieckie"
    },
    {
      "area": "119.20",
      "county": "ostrowski",
      "id": "1249",
      "name": "Wąsewo",
      "voivodeship": "mazowieckie"
    },
    {
      "area": "35.45",
      "county": "węgrowski",
      "id": "1250",
      "name": "Węgrów",
      "voivodeship": "mazowieckie"
    },
    {
      "area": "102.12",
      "county": "otwocki",
      "id": "1251",
      "name": "Wiązowna",
      "voivodeship": "mazowieckie"
    },
    {
      "area": "119.81",
      "county": "mławski",
      "id": "1252",
      "name": "Wieczfnia Kościelna",
      "voivodeship": "mazowieckie"
    },
    {
      "area": "102.23",
      "county": "legionowski",
      "id": "1253",
      "name": "Wieliszew",
      "voivodeship": "mazowieckie"
    },
    {
      "area": "104.03",
      "county": "przysuski",
      "id": "1254",
      "name": "Wieniawa",
      "voivodeship": "mazowieckie"
    },
    {
      "area": "93.97",
      "county": "radomski",
      "id": "1255",
      "name": "Wierzbica",
      "voivodeship": "mazowieckie"
    },
    {
      "area": "103.09",
      "county": "węgrowski",
      "id": "1256",
      "name": "Wierzbno",
      "voivodeship": "mazowieckie"
    },
    {
      "area": "119.13",
      "county": "garwoliński",
      "id": "1257",
      "name": "Wilga",
      "voivodeship": "mazowieckie"
    },
    {
      "area": "115.09",
      "county": "pułtuski",
      "id": "1258",
      "name": "Winnica",
      "voivodeship": "mazowieckie"
    },
    {
      "area": "150.94",
      "county": "żyrardowski",
      "id": "1259",
      "name": "Wiskitki",
      "voivodeship": "mazowieckie"
    },
    {
      "area": "125.87",
      "county": "siedlecki",
      "id": "1260",
      "name": "Wiśniew",
      "voivodeship": "mazowieckie"
    },
    {
      "area": "99.31",
      "county": "mławski",
      "id": "1261",
      "name": "Wiśniewo",
      "voivodeship": "mazowieckie"
    },
    {
      "area": "115.66",
      "county": "siedlecki",
      "id": "1262",
      "name": "Wodynie",
      "voivodeship": "mazowieckie"
    },
    {
      "area": "82.85",
      "county": "radomski",
      "id": "1263",
      "name": "Wolanów",
      "voivodeship": "mazowieckie"
    },
    {
      "area": "59.52",
      "county": "wołomiński",
      "id": "1264",
      "name": "Wołomin",
      "voivodeship": "mazowieckie"
    },
    {
      "area": "165.60",
      "county": "wyszkowski",
      "id": "1265",
      "name": "Wyszków",
      "voivodeship": "mazowieckie"
    },
    {
      "area": "97.93",
      "county": "płocki",
      "id": "1266",
      "name": "Wyszogród",
      "voivodeship": "mazowieckie"
    },
    {
      "area": "104.31",
      "county": "białobrzeski",
      "id": "1267",
      "name": "Wyśmierzyce",
      "voivodeship": "mazowieckie"
    },
    {
      "area": "92.03",
      "county": "wyszkowski",
      "id": "1268",
      "name": "Zabrodzie",
      "voivodeship": "mazowieckie"
    },
    {
      "area": "71.42",
      "county": "nowodworski",
      "id": "1269",
      "name": "Zakroczym",
      "voivodeship": "mazowieckie"
    },
    {
      "area": "96.15",
      "county": "radomski",
      "id": "1270",
      "name": "Zakrzew",
      "voivodeship": "mazowieckie"
    },
    {
      "area": "111.65",
      "county": "płoński",
      "id": "1271",
      "name": "Załuski",
      "voivodeship": "mazowieckie"
    },
    {
      "area": "88.90",
      "county": "ostrowski",
      "id": "1272",
      "name": "Zaręby Kościelne",
      "voivodeship": "mazowieckie"
    },
    {
      "area": "121.62",
      "county": "pułtuski",
      "id": "1273",
      "name": "Zatory",
      "voivodeship": "mazowieckie"
    },
    {
      "area": "186.09",
      "county": "sierpecki",
      "id": "1274",
      "name": "Zawidz",
      "voivodeship": "mazowieckie"
    },
    {
      "area": "11.13",
      "county": "wołomiński",
      "id": "1275",
      "name": "Ząbki",
      "voivodeship": "mazowieckie"
    },
    {
      "area": "210.75",
      "county": "siedlecki",
      "id": "1276",
      "name": "Zbuczyn",
      "voivodeship": "mazowieckie"
    },
    {
      "area": "79.23",
      "county": "wołomiński",
      "id": "1277",
      "name": "Zielonka",
      "voivodeship": "mazowieckie"
    },
    {
      "area": "161.12",
      "county": "zwoleński",
      "id": "1278",
      "name": "Zwoleń",
      "voivodeship": "mazowieckie"
    },
    {
      "area": "105.61",
      "county": "grodziski",
      "id": "1279",
      "name": "Żabia Wola",
      "voivodeship": "mazowieckie"
    },
    {
      "area": "87.64",
      "county": "garwoliński",
      "id": "1280",
      "name": "Żelechów",
      "voivodeship": "mazowieckie"
    },
    {
      "area": "132.44",
      "county": "żuromiński",
      "id": "1281",
      "name": "Żuromin",
      "voivodeship": "mazowieckie"
    },
    {
      "area": "14.35",
      "county": "żyrardowski",
      "id": "1282",
      "name": "Żyrardów",
      "voivodeship": "mazowieckie"
    }
  ]
}